georeader/SolarIrradiance_Thuillier.csv
georeader/__init__.py
georeader/abstract_reader.py
georeader/dataarray.py
georeader/geotensor.py
georeader/griddata.py
georeader/mosaic.py
georeader/plot.py
georeader/rasterio_reader.py
georeader/rasterize.py
georeader/read.py
georeader/readers/S2_SAFE_reader.py
georeader/readers/__init__.py
georeader/readers/download_pv_product.py
georeader/readers/download_utils.py
georeader/readers/ee_image.py
georeader/readers/ee_query.py
georeader/readers/ee_utils.py
georeader/readers/emit.py
georeader/readers/enmap.py
georeader/readers/prisma.py
georeader/readers/probav_image_operational.py
georeader/readers/query_utils.py
georeader/readers/scihubcopernicus_query.py
georeader/readers/spotvgt_image_operational.py
georeader/readers/tileserver.py
georeader/reflectance.py
georeader/save.py
georeader/save_cog.py
georeader/slices.py
georeader/vectorize.py
georeader/window_utils.py
georeader_spaceml-1.5.9.dist-info/LICENSE
georeader_spaceml-1.5.9.dist-info/METADATA
georeader_spaceml-1.5.9.dist-info/WHEEL
georeader_spaceml-1.5.9.dist-info/RECORD
