Metadata-Version: 2.1
Name: georeader-spaceml
Version: 1.5.9
Summary: 🛰️ Process raster data in python
Home-page: https://github.com/spaceml-org/georeader
License: 	LGPL-3.0
Author: Gonzalo Mateo-García
Requires-Python: >=3.11,<4.0
Classifier: License :: Other/Proprietary License
Classifier: Programming Language :: Python :: 3
Classifier: Programming Language :: Python :: 3.11
Classifier: Programming Language :: Python :: 3.12
Classifier: Programming Language :: Python :: 3.13
Requires-Dist: geopandas (>=1)
Requires-Dist: mercantile (>=1)
Requires-Dist: numpy (>=1)
Requires-Dist: rasterio (>=1)
Requires-Dist: shapely (>=2)
Project-URL: Documentation, https://spaceml-org.github.io/georeader/
Project-URL: Repository, https://github.com/spaceml-org/georeader
